{
  "id": "2447702",
  "name": "个人博客",
  "font_family": "iconfont",
  "css_prefix_text": "icon-",
  "description": "",
  "glyphs": [
    {
      "icon_id": "1030072",
      "name": "hide",
      "font_class": "hide",
      "unicode": "e76b",
      "unicode_decimal": 59243
    },
    {
      "icon_id": "5315767",
      "name": "show",
      "font_class": "show1",
      "unicode": "e760",
      "unicode_decimal": 59232
    },
    {
      "icon_id": "386336",
      "name": "勾",
      "font_class": "gou",
      "unicode": "e61a",
      "unicode_decimal": 58906
    },
    {
      "icon_id": "19449153",
      "name": "推荐",
      "font_class": "tuijian",
      "unicode": "e631",
      "unicode_decimal": 58929
    },
    {
      "icon_id": "915604",
      "name": "分类 (1)",
      "font_class": "menu",
      "unicode": "e670",
      "unicode_decimal": 58992
    },
    {
      "icon_id": "538852",
      "name": "TAG",
      "font_class": "tag",
      "unicode": "e605",
      "unicode_decimal": 58885
    },
    {
      "icon_id": "1120961",
      "name": "编辑",
      "font_class": "edit",
      "unicode": "e619",
      "unicode_decimal": 58905
    },
    {
      "icon_id": "16563628",
      "name": "查看",
      "font_class": "show",
      "unicode": "e606",
      "unicode_decimal": 58886
    },
    {
      "icon_id": "18311262",
      "name": "删 除",
      "font_class": "delete",
      "unicode": "e63d",
      "unicode_decimal": 58941
    },
    {
      "icon_id": "13253757",
      "name": "edit",
      "font_class": "edit-blogs",
      "unicode": "e601",
      "unicode_decimal": 58881
    },
    {
      "icon_id": "809934",
      "name": "time",
      "font_class": "icon-time",
      "unicode": "e639",
      "unicode_decimal": 58937
    },
    {
      "icon_id": "1393759",
      "name": "search",
      "font_class": "search",
      "unicode": "e71f",
      "unicode_decimal": 59167
    },
    {
      "icon_id": "809937",
      "name": "user",
      "font_class": "icon-user",
      "unicode": "e63c",
      "unicode_decimal": 58940
    },
    {
      "icon_id": "10166323",
      "name": "home",
      "font_class": "home",
      "unicode": "e62f",
      "unicode_decimal": 58927
    }
  ]
}
